fluid/__init__.py
fluid/algo_random.py
fluid/ashaparallel.py
fluid/executor.py
fluid/fluid_executor.py
fluid/my_bracket.py
fluid/my_run.py
fluid/perf_manager.py
fluid/ray_custom_gpu_res.py
fluid/runnner.py
fluid/scheduler.py
fluid/syncbohb.py
fluid/trainer.py
fluidexec-0.1.0rc0.dist-info/LICENSE
fluidexec-0.1.0rc0.dist-info/WHEEL
fluidexec-0.1.0rc0.dist-info/METADATA
fluidexec-0.1.0rc0.dist-info/RECORD
