Metadata-Version: 2.1
Name: fluidexec
Version: 0.1.0rc0
Summary: Resource-aware hyperparameter tuning execution engine
Home-page: https://github.com/SymbioticLab/fluid
License: Apache-2.0
Author: Peifeng
Author-email: peifeng@umich.edu
Requires-Python: >=3.6,<3.7
Classifier: License :: OSI Approved :: Apache Software License
Classifier: Programming Language :: Python :: 3
Classifier: Programming Language :: Python :: 3.6
Provides-Extra: exp
Requires-Dist: ConfigSpace; extra == "exp"
Requires-Dist: hpbandster; extra == "exp"
Requires-Dist: numpy
Requires-Dist: pandas; extra == "exp"
Requires-Dist: ray[tune] (==0.8.5)
Requires-Dist: requests
Project-URL: Repository, https://github.com/SymbioticLab/fluid
